<?xml version="1.0" encoding="utf-8"?>
<tv xmlns:xsi="http://www.w3.org/2001/XMLSchema-instance" xmlns:xsd="http://www.w3.org/2001/XMLSchema" source-info-name="Magic button (EUW1Z2XAW16VP5)" xsi:noNamespaceSchemaLocation="http://epgs.vimn.com/xsd/ViacomXmlTv.xsd">
  <channel id="MTV 80s">
    <display-name lang="en">MTV 80s</display-name>
  </channel>
  <programme is_live="false" start="20240806070000 +0200" air_time_start="20240806070000 +0200" air_time_end="20240806100000 +0200" stop="20240806100000 +0200" start_utc="20240806050000 +0000" stop_utc="20240806080000 +0000" air_time_start_utc="20240806050000 +0000" air_time_end_utc="20240806080000 +0000" channel="MTV 80s">
    <title lang="en">I Want My MTV 80s!</title>
    <sub-title lang="en"></sub-title>
    <original-title>I Want My MTV 80s!</original-title>
    <original-episode-title />
    <desc_short lang="en">It's non-stop global nostalgia right here at MTV 80s - and that's what we want, right now!</desc_short>
    <keywords />
    <dvb_event_id>18792382758668</dvb_event_id>
    <dvbsi_genre level1="0x6" level2="0x1" />
    <ott_mobile>true</ott_mobile>
    <ott_internet>true</ott_internet>
    <tve_mobile>true</tve_mobile>
    <tve_internet>true</tve_internet>
    <vod_catchup>false</vod_catchup>
    <start_over>true</start_over>
    <npvr>false</npvr>
    <production_year></production_year>
    <credits />
    <category>Music - Rock &amp; Pop</category>
    <length units="seconds">10800</length>
    <production-country />
    <audio_list />
    <identifier>9014341411527</identifier>
    <video>
      <aspect>4:3</aspect>
      <quality />
    </video>
    <subtitles />
    <audio_described>false</audio_described>
    <invision_signing>false</invision_signing>
  </programme>
  <programme is_live="false" start="20240806100000 +0200" air_time_start="20240806100000 +0200" air_time_end="20240806150000 +0200" stop="20240806150000 +0200" start_utc="20240806080000 +0000" stop_utc="20240806130000 +0000" air_time_start_utc="20240806080000 +0000" air_time_end_utc="20240806130000 +0000" channel="MTV 80s">
    <title lang="en">1986 Wrapped!</title>
    <sub-title lang="en"></sub-title>
    <original-title>1986 Wrapped!</original-title>
    <original-episode-title />
    <desc_short lang="en">We're powering-up the MTV time machine and going back to celebrate the best years of our lives! This time we land in 1986 ...and you can expect hits from Five Star, The Bangles and Madonna!</desc_short>
    <keywords />
    <dvb_event_id>18792382964668</dvb_event_id>
    <dvbsi_genre level1="0x6" level2="0x1" />
    <ott_mobile>true</ott_mobile>
    <ott_internet>true</ott_internet>
    <tve_mobile>true</tve_mobile>
    <tve_internet>true</tve_internet>
    <vod_catchup>false</vod_catchup>
    <start_over>true</start_over>
    <npvr>false</npvr>
    <production_year>0</production_year>
    <credits />
    <category>Music - Rock &amp; Pop</category>
    <length units="seconds">18000</length>
    <production-country />
    <audio_list />
    <identifier>13771509982527</identifier>
    <video>
      <aspect>4:3</aspect>
      <quality />
    </video>
    <subtitles />
    <audio_described>false</audio_described>
    <invision_signing>false</invision_signing>
  </programme>
  <programme is_live="false" start="20240806150000 +0200" air_time_start="20240806150000 +0200" air_time_end="20240806160000 +0200" stop="20240806160000 +0200" start_utc="20240806130000 +0000" stop_utc="20240806140000 +0000" air_time_start_utc="20240806130000 +0000" air_time_end_utc="20240806140000 +0000" channel="MTV 80s">
    <title lang="en">Let's Hear It For The Girls!</title>
    <sub-title lang="en"></sub-title>
    <original-title>Let's Hear It For The Girls!</original-title>
    <original-episode-title />
    <desc_short lang="en">From Madonna to Whitney, Annie to Tina, we're all about the women that shaped the glorious '80s - so let's hear it for these hit-making girls!</desc_short>
    <keywords />
    <dvb_event_id>18792383986668</dvb_event_id>
    <dvbsi_genre level1="0x6" level2="0x1" />
    <ott_mobile>true</ott_mobile>
    <ott_internet>true</ott_internet>
    <tve_mobile>true</tve_mobile>
    <tve_internet>true</tve_internet>
    <vod_catchup>false</vod_catchup>
    <start_over>true</start_over>
    <npvr>false</npvr>
    <production_year></production_year>
    <credits />
    <category>Music - Rock &amp; Pop</category>
    <length units="seconds">3600</length>
    <production-country />
    <audio_list />
    <identifier>16418822744527</identifier>
    <video>
      <aspect>4:3</aspect>
      <quality />
    </video>
    <subtitles />
    <audio_described>false</audio_described>
    <invision_signing>false</invision_signing>
  </programme>
  <programme is_live="false" start="20240806160000 +0200" air_time_start="20240806160000 +0200" air_time_end="20240806210000 +0200" stop="20240806210000 +0200" start_utc="20240806140000 +0000" stop_utc="20240806190000 +0000" air_time_start_utc="20240806140000 +0000" air_time_end_utc="20240806190000 +0000" channel="MTV 80s">
    <title lang="en">Let's Dance! 50 Vids with...</title>
    <sub-title lang="en"></sub-title>
    <original-title>Let's Dance! 50 Vids with... </original-title>
    <original-episode-title />
    <desc_short lang="en">...80s Moves! We hope you're ready to get up and groove as we bring you 50 of the best dance moves ever recorded in '80s music videos!</desc_short>
    <keywords />
    <dvb_event_id>18792387257668</dvb_event_id>
    <dvbsi_genre level1="0x6" level2="0x1" />
    <ott_mobile>false</ott_mobile>
    <ott_internet>false</ott_internet>
    <tve_mobile>false</tve_mobile>
    <tve_internet>false</tve_internet>
    <vod_catchup>false</vod_catchup>
    <start_over>false</start_over>
    <npvr>false</npvr>
    <production_year></production_year>
    <credits />
    <category>Music - Rock &amp; Pop</category>
    <length units="seconds">18000</length>
    <production-country />
    <audio_list />
    <identifier>18783546323527</identifier>
    <video>
      <aspect>4:3</aspect>
      <quality />
    </video>
    <subtitles />
    <audio_described>false</audio_described>
    <invision_signing>false</invision_signing>
  </programme>
  <programme is_live="false" start="20240806210000 +0200" air_time_start="20240806210000 +0200" air_time_end="20240806220000 +0200" stop="20240806220000 +0200" start_utc="20240806190000 +0000" stop_utc="20240806200000 +0000" air_time_start_utc="20240806190000 +0000" air_time_end_utc="20240806200000 +0000" channel="MTV 80s">
    <title lang="en">I Want My MTV 80s!</title>
    <sub-title lang="en"></sub-title>
    <original-title>I Want My MTV 80s!</original-title>
    <original-episode-title />
    <desc_short lang="en">It's non-stop global nostalgia right here at MTV 80s - and that's what we want, right now!</desc_short>
    <keywords />
    <dvb_event_id>18792387487668</dvb_event_id>
    <dvbsi_genre level1="0x6" level2="0x1" />
    <ott_mobile>true</ott_mobile>
    <ott_internet>true</ott_internet>
    <tve_mobile>true</tve_mobile>
    <tve_internet>true</tve_internet>
    <vod_catchup>false</vod_catchup>
    <start_over>true</start_over>
    <npvr>false</npvr>
    <production_year></production_year>
    <credits />
    <category>Music - Rock &amp; Pop</category>
    <length units="seconds">3600</length>
    <production-country />
    <audio_list />
    <identifier>9014341411527</identifier>
    <video>
      <aspect>4:3</aspect>
      <quality />
    </video>
    <subtitles />
    <audio_described>false</audio_described>
    <invision_signing>false</invision_signing>
  </programme>
  <programme is_live="false" start="20240806220000 +0200" air_time_start="20240806220000 +0200" air_time_end="20240807030000 +0200" stop="20240807030000 +0200" start_utc="20240806200000 +0000" stop_utc="20240807010000 +0000" air_time_start_utc="20240806200000 +0000" air_time_end_utc="20240807010000 +0000" channel="MTV 80s">
    <title lang="en">Electric Dreams: 50 Synth-Pop Hits</title>
    <sub-title lang="en"></sub-title>
    <original-title>Electric Dreams: 50 Synth-Pop Hits</original-title>
    <original-episode-title />
    <desc_short lang="en">MTV80s wouldn't be MTV80s without a glorious synthesiser breakdown and flamboyant dance move... So stick around as we play 50 videos that simply ooze 1980s synth-pop!</desc_short>
    <keywords />
    <dvb_event_id>18792387568668</dvb_event_id>
    <dvbsi_genre level1="0x6" level2="0x1" />
    <ott_mobile>false</ott_mobile>
    <ott_internet>false</ott_internet>
    <tve_mobile>false</tve_mobile>
    <tve_internet>false</tve_internet>
    <vod_catchup>false</vod_catchup>
    <start_over>false</start_over>
    <npvr>false</npvr>
    <production_year></production_year>
    <credits />
    <category>Music - Rock &amp; Pop</category>
    <length units="seconds">18000</length>
    <production-country />
    <audio_list />
    <identifier>18783529274527</identifier>
    <video>
      <aspect>4:3</aspect>
      <quality />
    </video>
    <subtitles />
    <audio_described>false</audio_described>
    <invision_signing>false</invision_signing>
  </programme>
  <programme is_live="false" start="20240807030000 +0200" air_time_start="20240807030000 +0200" air_time_end="20240807050000 +0200" stop="20240807050000 +0200" start_utc="20240807010000 +0000" stop_utc="20240807030000 +0000" air_time_start_utc="20240807010000 +0000" air_time_end_utc="20240807030000 +0000" channel="MTV 80s">
    <title lang="en">I Want My MTV 80s!</title>
    <sub-title lang="en"></sub-title>
    <original-title>I Want My MTV 80s!</original-title>
    <original-episode-title />
    <desc_short lang="en">It's non-stop global nostalgia right here at MTV 80s - and that's what we want, right now!</desc_short>
    <keywords />
    <dvb_event_id>18792387838668</dvb_event_id>
    <dvbsi_genre level1="0x6" level2="0x1" />
    <ott_mobile>true</ott_mobile>
    <ott_internet>true</ott_internet>
    <tve_mobile>true</tve_mobile>
    <tve_internet>true</tve_internet>
    <vod_catchup>false</vod_catchup>
    <start_over>true</start_over>
    <npvr>false</npvr>
    <production_year></production_year>
    <credits />
    <category>Music - Rock &amp; Pop</category>
    <length units="seconds">7200</length>
    <production-country />
    <audio_list />
    <identifier>9014341411527</identifier>
    <video>
      <aspect>4:3</aspect>
      <quality />
    </video>
    <subtitles />
    <audio_described>false</audio_described>
    <invision_signing>false</invision_signing>
  </programme>
</tv>